{
  "Id": "1-5939be0f-4093c776b3872d9ce76ea530",
  "Duration": 0.047,
  "Segments": [
    {
      "Id": "7ce3b549fdc27e76",
      "Document": {
        "id": "7ce3b549fdc27e76",
        "name": "readValuesFunction",
        "start_time": 1496956431.007,
        "end_time": 1496956431.044,
        "http": {
          "response": {
            "status": 200
          }
        },
        "aws": {
          "request_id": "5ea5605b-4c8f-11e7-94f9-c35f9838f516"
        },
        "trace_id": "1-5939be0f-4093c776b3872d9ce76ea530",
        "origin": "AWS::Lambda",
        "resource_arn": "arn:aws:lambda:eu-west-1:797753712737:function:readValuesFunction"
      }
    },
    {
      "Id": "267bcf627c151d61",
      "Document": {
        "id": "267bcf627c151d61",
        "name": "readValuesFunction",
        "start_time": 1496956430.997,
        "end_time": 1496956431.028,
        "parent_id": "7ce3b549fdc27e76",
        "aws": {
          "function_arn": "arn:aws:lambda:eu-west-1:797753712737:function:readValuesFunction",
          "resource_names": [
            "readValuesFunction"
          ],
          "account_id": "797753712737"
        },
        "trace_id": "1-5939be0f-4093c776b3872d9ce76ea530",
        "origin": "AWS::Lambda::Function",
        "subsegments": [
          {
            "id": "dc427e79a8bef5b7",
            "name": "DynamoDB",
            "start_time": 1496956430.998,
            "end_time": 1496956431.026,
            "http": {
              "response": {
                "status": 200
              }
            },
            "aws": {
              "operation": "Query",
              "region": "eu-west-1",
              "request_id": "V1EUODA9KA4HL5MCL7ULD9SSN7VV4KQNSO5AEMVJF66Q9ASUAAJG",
              "retries": 0,
              "limit": 1000,
              "select": "ALL_ATTRIBUTES",
              "table_name": "ValuesTable",
              "resource_names": [
                "ValuesTable"
              ]
            },
            "namespace": "aws",
            "subsegments": [
              {
                "id": "ca644bae1533efc9",
                "name": "DynamoDBCostradamus",
                "start_time": 1496956431.026,
                "end_time": 1496956431.026,
                "metadata": {
                  "DynamoDBCostradamus": {
                    "consumptions": {
                      "CapacityUnits": {
                        "val": 3,
                        "type": "RCU"
                      },
                      "PayloadSize": {
                        "val": 54059,
                        "type": "B"
                      },
                      "Latency": {
                        "val": 29,
                        "type": "MS"
                      }
                    }
                  }
                },
                "cost": {
                  "MonetaryCost": {
                    "type": "NANO-USD",
                    "val": 123
                  },
                  "ProvisioningAmountWaste": {
                    "type": "B",
                    "val": 145941
                  },
                  "ProvisioningTimeWaste": {
                    "type": "MS",
                    "val": 3599971
                  },
                  "MeteringAmountWaste": {
                    "type": "B",
                    "val": 1941
                  },
                  "MeteringTimeWaste": {
                    "type": "MS",
                    "val": 971
                  }
                }
              }
            ],
            "consumptions": {
              "CapacityUnits": {
                "val": 3,
                "type": "RCU"
              },
              "PayloadSize": {
                "val": 54059,
                "type": "B"
              },
              "Latency": {
                "val": 29,
                "type": "MS"
              }
            },
            "cost": {
              "MonetaryCost": {
                "type": "NANO-USD",
                "val": 123
              },
              "ProvisioningAmountWaste": {
                "type": "B",
                "val": 145941
              },
              "ProvisioningTimeWaste": {
                "type": "MS",
                "val": 3599971
              },
              "MeteringAmountWaste": {
                "type": "B",
                "val": 1941
              },
              "MeteringTimeWaste": {
                "type": "MS",
                "val": 971
              }
            }
          },
          {
            "id": "beba618d8d4aead7",
            "name": "LambdaCostradamus",
            "start_time": 1496956430.997,
            "end_time": 1496956430.998,
            "metadata": {
              "LambdaCostradamus": {
                "RequestId": "5ea5605b-4c8f-11e7-94f9-c35f9838f516"
              }
            }
          }
        ],
        "consumptions": {
          "Duration": {
            "val": 31,
            "type": "ms"
          },
          "BilledDuration": {
            "val": 100,
            "type": "ms"
          },
          "MemorySize": {
            "val": 1024,
            "type": "MB"
          },
          "MaxMemoryUsed": {
            "val": 50,
            "type": "MB"
          }
        },
        "cost": {
          "MonetaryCost": {
            "type": "NANO-USD",
            "val": 1667
          },
          "ProvisioningAmountWaste": {
            "type": "B",
            "val": 0
          },
          "ProvisioningTimeWaste": {
            "type": "MS",
            "val": 0
          },
          "MeteringAmountWaste": {
            "type": "MB",
            "val": 974
          },
          "MeteringTimeWaste": {
            "type": "MS",
            "val": 69
          }
        }
      }
    },
    {
      "Id": "0cf43090043f0256",
      "Document": {
        "id": "0cf43090043f0256",
        "name": "DynamoDB",
        "start_time": 1496956430.998,
        "end_time": 1496956431.026,
        "parent_id": "dc427e79a8bef5b7",
        "inferred": true,
        "http": {
          "response": {
            "status": 200
          }
        },
        "aws": {
          "operation": "Query",
          "region": "eu-west-1",
          "request_id": "V1EUODA9KA4HL5MCL7ULD9SSN7VV4KQNSO5AEMVJF66Q9ASUAAJG",
          "retries": 0,
          "limit": 1000,
          "select": "ALL_ATTRIBUTES",
          "table_name": "ValuesTable",
          "resource_names": [
            "ValuesTable"
          ]
        },
        "trace_id": "1-5939be0f-4093c776b3872d9ce76ea530",
        "origin": "AWS::DynamoDB::Table"
      }
    }
  ]
}