{
  "Id": "1-5939c4a3-08104439b1999caa32468f78",
  "Duration": 8.342000007629395,
  "Segments": [
    {
      "Id": "152b013f4a40e180",
      "Document": {
        "id": "152b013f4a40e180",
        "name": "ingestValueFunction",
        "start_time": 1496958115.825,
        "end_time": 1496958116.063,
        "parent_id": "35cf55ca9bfe555e",
        "aws": {
          "function_arn": "arn:aws:lambda:us-east-1:797753712737:function:ingestValueFunction",
          "resource_names": [
            "ingestValueFunction"
          ],
          "account_id": "797753712737"
        },
        "trace_id": "1-5939c4a3-08104439b1999caa32468f78",
        "origin": "AWS::Lambda::Function",
        "subsegments": [
          {
            "id": "a82aabbfcde2e782",
            "name": "Lambda",
            "start_time": 1496958115.83,
            "end_time": 1496958116.005,
            "http": {
              "response": {
                "status": 202
              }
            },
            "aws": {
              "operation": "Invoke",
              "region": "us-east-1",
              "request_id": "4af9d5cc-4c93-11e7-8914-ebf44942154e",
              "retries": 0,
              "function_name": "persistValueFunction",
              "invocation_type": "Event",
              "resource_names": [
                "persistValueFunction"
              ]
            },
            "namespace": "aws"
          },
          {
            "id": "33ccbd878b7ccdfb",
            "name": "Lambda",
            "start_time": 1496958115.869,
            "end_time": 1496958116.062,
            "http": {
              "response": {
                "status": 202
              }
            },
            "aws": {
              "operation": "Invoke",
              "region": "us-east-1",
              "request_id": "4af960b1-4c93-11e7-9ebe-875b2f8c332a",
              "retries": 0,
              "function_name": "predictValueFunction",
              "invocation_type": "Event",
              "resource_names": [
                "predictValueFunction"
              ]
            },
            "namespace": "aws"
          },
          {
            "id": "fc972df35a999280",
            "name": "LambdaCostradamus",
            "start_time": 1496958115.828,
            "end_time": 1496958115.828,
            "metadata": {
              "LambdaCostradamus": {
                "RequestId": "4adf4869-4c93-11e7-a18a-532955ff83a2"
              }
            }
          }
        ],
        "consumptions": {
          "Duration": {
            "val": 237,
            "type": "ms"
          },
          "BilledDuration": {
            "val": 300,
            "type": "ms"
          },
          "MemorySize": {
            "val": 128,
            "type": "MB"
          },
          "MaxMemoryUsed": {
            "val": 43,
            "type": "MB"
          }
        },
        "cost": {
          "MonetaryCost": {
            "type": "NANO-USD",
            "val": 624
          },
          "ProvisioningAmountWaste": {
            "type": "B",
            "val": 0
          },
          "ProvisioningTimeWaste": {
            "type": "MS",
            "val": 0
          },
          "MeteringAmountWaste": {
            "type": "MB",
            "val": 85
          },
          "MeteringTimeWaste": {
            "type": "MS",
            "val": 63
          }
        }
      }
    },
    {
      "Id": "2c77475d679e4f6a",
      "Document": {
        "id": "2c77475d679e4f6a",
        "name": "persistValueFunction",
        "start_time": 1496958116.041,
        "end_time": 1496958116.108,
        "parent_id": "6915bd5adf047756",
        "aws": {
          "function_arn": "arn:aws:lambda:us-east-1:797753712737:function:persistValueFunction",
          "resource_names": [
            "persistValueFunction"
          ],
          "account_id": "797753712737"
        },
        "trace_id": "1-5939c4a3-08104439b1999caa32468f78",
        "origin": "AWS::Lambda::Function",
        "subsegments": [
          {
            "id": "097e6d82e2062caa",
            "name": "LambdaCostradamus",
            "start_time": 1496958116.041,
            "end_time": 1496958116.041,
            "metadata": {
              "LambdaCostradamus": {
                "RequestId": "4af9d5cc-4c93-11e7-8914-ebf44942154e"
              }
            }
          },
          {
            "id": "877ef218a4249b61",
            "name": "DynamoDB",
            "start_time": 1496958116.042,
            "end_time": 1496958116.107,
            "http": {
              "response": {
                "status": 200
              }
            },
            "aws": {
              "operation": "PutItem",
              "region": "us-east-1",
              "request_id": "9UVLM259BBJSO3FMTON9OE8T4BVV4KQNSO5AEMVJF66Q9ASUAAJG",
              "retries": 0,
              "table_name": "ValuesTable",
              "resource_names": [
                "ValuesTable"
              ]
            },
            "namespace": "aws",
            "subsegments": [
              {
                "id": "cec3ca4e1410189e",
                "name": "DynamoDBCostradamus",
                "start_time": 1496958116.107,
                "end_time": 1496958116.107,
                "metadata": {
                  "DynamoDBCostradamus": {
                    "consumptions": {
                      "CapacityUnits": {
                        "val": 1,
                        "type": "WCU"
                      },
                      "PayloadSize": {
                        "val": 182,
                        "type": "B"
                      },
                      "Latency": {
                        "val": 66,
                        "type": "MS"
                      }
                    }
                  }
                },
                "cost": {
                  "MonetaryCost": {
                    "type": "NANO-USD",
                    "val": 181
                  },
                  "ProvisioningAmountWaste": {
                    "type": "B",
                    "val": 9818
                  },
                  "ProvisioningTimeWaste": {
                    "type": "MS",
                    "val": 3599934
                  },
                  "MeteringAmountWaste": {
                    "type": "B",
                    "val": 818
                  },
                  "MeteringTimeWaste": {
                    "type": "MS",
                    "val": 934
                  }
                }
              }
            ],
            "consumptions": {
              "CapacityUnits": {
                "val": 1,
                "type": "WCU"
              },
              "PayloadSize": {
                "val": 182,
                "type": "B"
              },
              "Latency": {
                "val": 66,
                "type": "MS"
              }
            },
            "cost": {
              "MonetaryCost": {
                "type": "NANO-USD",
                "val": 181
              },
              "ProvisioningAmountWaste": {
                "type": "B",
                "val": 9818
              },
              "ProvisioningTimeWaste": {
                "type": "MS",
                "val": 3599934
              },
              "MeteringAmountWaste": {
                "type": "B",
                "val": 818
              },
              "MeteringTimeWaste": {
                "type": "MS",
                "val": 934
              }
            }
          }
        ],
        "consumptions": {
          "Duration": {
            "val": 67,
            "type": "ms"
          },
          "BilledDuration": {
            "val": 100,
            "type": "ms"
          },
          "MemorySize": {
            "val": 128,
            "type": "MB"
          },
          "MaxMemoryUsed": {
            "val": 44,
            "type": "MB"
          }
        },
        "cost": {
          "MonetaryCost": {
            "type": "NANO-USD",
            "val": 208
          },
          "ProvisioningAmountWaste": {
            "type": "B",
            "val": 0
          },
          "ProvisioningTimeWaste": {
            "type": "MS",
            "val": 0
          },
          "MeteringAmountWaste": {
            "type": "MB",
            "val": 84
          },
          "MeteringTimeWaste": {
            "type": "MS",
            "val": 33
          }
        }
      }
    },
    {
      "Id": "0c48bb546cc159ec",
      "Document": {
        "id": "0c48bb546cc159ec",
        "name": "predictValueFunction",
        "start_time": 1496958115.99,
        "end_time": 1496958116.056,
        "parent_id": "33ccbd878b7ccdfb",
        "http": {
          "response": {
            "status": 202
          }
        },
        "aws": {
          "request_id": "4af960b1-4c93-11e7-9ebe-875b2f8c332a"
        },
        "trace_id": "1-5939c4a3-08104439b1999caa32468f78",
        "origin": "AWS::Lambda",
        "resource_arn": "arn:aws:lambda:us-east-1:797753712737:function:predictValueFunction",
        "subsegments": [
          {
            "id": "2d55c9b3a2fed0db",
            "name": "Attempt #1",
            "start_time": 1496958116.087,
            "end_time": 1496958124.159,
            "http": {
              "response": {
                "status": 200
              }
            }
          },
          {
            "id": "2ce5bdd6b3b54334",
            "name": "Dwell Time",
            "start_time": 1496958115.99,
            "end_time": 1496958116.087,
            "http": {
              "response": {}
            }
          }
        ]
      }
    },
    {
      "Id": "102fb28654e012af",
      "Document": {
        "id": "102fb28654e012af",
        "name": "predictValueFunction",
        "start_time": 1496958120.324,
        "end_time": 1496958124.154,
        "parent_id": "2d55c9b3a2fed0db",
        "aws": {
          "function_arn": "arn:aws:lambda:us-east-1:797753712737:function:predictValueFunction",
          "resource_names": [
            "predictValueFunction"
          ],
          "account_id": "797753712737"
        },
        "trace_id": "1-5939c4a3-08104439b1999caa32468f78",
        "origin": "AWS::Lambda::Function",
        "subsegments": [
          {
            "id": "68471d8e36cb6eb7",
            "name": "Initialization",
            "start_time": 1496958117.374,
            "end_time": 1496958120.249,
            "aws": {
              "function_arn": "arn:aws:lambda:us-east-1:797753712737:function:predictValueFunction"
            }
          },
          {
            "id": "d9040fc124635a6b",
            "name": "LambdaCostradamus",
            "start_time": 1496958120.326,
            "end_time": 1496958120.327,
            "metadata": {
              "LambdaCostradamus": {
                "RequestId": "4af960b1-4c93-11e7-9ebe-875b2f8c332a"
              }
            }
          },
          {
            "id": "5661694f9e3a2899",
            "name": "DynamoDB",
            "start_time": 1496958120.494,
            "end_time": 1496958122.768,
            "http": {
              "response": {
                "status": 200
              }
            },
            "aws": {
              "operation": "Query",
              "region": "us-east-1",
              "request_id": "U2QUEA877F5LBJQJ1ATCIE3N1JVV4KQNSO5AEMVJF66Q9ASUAAJG",
              "retries": 0,
              "limit": 100,
              "select": "ALL_ATTRIBUTES",
              "table_name": "ValuesTable",
              "resource_names": [
                "ValuesTable"
              ]
            },
            "namespace": "aws",
            "subsegments": [
              {
                "id": "9fc72bf133c0bdec",
                "name": "DynamoDB",
                "start_time": 1496958122.919,
                "end_time": 1496958123.875,
                "http": {
                  "response": {
                    "status": 200
                  }
                },
                "aws": {
                  "operation": "PutItem",
                  "region": "us-east-1",
                  "request_id": "7C1QGS6QQ9AGDVN6E4V8L6KP0JVV4KQNSO5AEMVJF66Q9ASUAAJG",
                  "retries": 0,
                  "table_name": "PredictionsTable",
                  "resource_names": [
                    "PredictionsTable"
                  ]
                },
                "namespace": "aws",
                "subsegments": [
                  {
                    "id": "17ed65112e9123d9",
                    "name": "DynamoDBCostradamus",
                    "start_time": 1496958123.876,
                    "end_time": 1496958123.876,
                    "metadata": {
                      "DynamoDBCostradamus": {
                        "consumptions": {
                          "CapacityUnits": {
                            "val": 1,
                            "type": "WCU"
                          },
                          "PayloadSize": {
                            "val": 182,
                            "type": "B"
                          },
                          "Latency": {
                            "val": 957,
                            "type": "MS"
                          }
                        }
                      }
                    },
                    "cost": {
                      "MonetaryCost": {
                        "type": "NANO-USD",
                        "val": 181
                      },
                      "ProvisioningAmountWaste": {
                        "type": "B",
                        "val": 9818
                      },
                      "ProvisioningTimeWaste": {
                        "type": "MS",
                        "val": 3599043
                      },
                      "MeteringAmountWaste": {
                        "type": "B",
                        "val": 818
                      },
                      "MeteringTimeWaste": {
                        "type": "MS",
                        "val": 43
                      }
                    }
                  }
                ],
                "consumptions": {
                  "CapacityUnits": {
                    "val": 1,
                    "type": "WCU"
                  },
                  "PayloadSize": {
                    "val": 182,
                    "type": "B"
                  },
                  "Latency": {
                    "val": 957,
                    "type": "MS"
                  }
                },
                "cost": {
                  "MonetaryCost": {
                    "type": "NANO-USD",
                    "val": 181
                  },
                  "ProvisioningAmountWaste": {
                    "type": "B",
                    "val": 9818
                  },
                  "ProvisioningTimeWaste": {
                    "type": "MS",
                    "val": 3599043
                  },
                  "MeteringAmountWaste": {
                    "type": "B",
                    "val": 818
                  },
                  "MeteringTimeWaste": {
                    "type": "MS",
                    "val": 43
                  }
                }
              },
              {
                "id": "dd5cb3f46b38aa20",
                "name": "Kinesis",
                "start_time": 1496958123.175,
                "end_time": 1496958123.834,
                "http": {
                  "response": {
                    "status": 200
                  }
                },
                "aws": {
                  "operation": "PutRecord",
                  "region": "us-east-1",
                  "request_id": "eb0973f8-bc00-e9ca-baba-b5137213c3ce",
                  "retries": 0
                },
                "namespace": "aws",
                "subsegments": [
                  {
                    "id": "37165a3d25836218",
                    "name": "KinesisCostradamus",
                    "start_time": 1496958123.835,
                    "end_time": 1496958123.835,
                    "metadata": {
                      "KinesisCostradamus": {
                        "consumptions": {
                          "PayloadSize": {
                            "val": 182,
                            "type": "B"
                          },
                          "Operation": {
                            "val": "WRITE",
                            "type": "KINESISOPERATION"
                          },
                          "Latency": {
                            "val": 660,
                            "type": "MS"
                          }
                        }
                      }
                    },
                    "cost": {
                      "MonetaryCost": {
                        "type": "NANO-USD",
                        "val": 118
                      }
                    }
                  }
                ],
                "consumptions": {
                  "PayloadSize": {
                    "val": 182,
                    "type": "B"
                  },
                  "Operation": {
                    "val": "WRITE",
                    "type": "KINESISOPERATION"
                  },
                  "Latency": {
                    "val": 660,
                    "type": "MS"
                  }
                },
                "cost": {
                  "MonetaryCost": {
                    "type": "NANO-USD",
                    "val": 118
                  }
                }
              },
              {
                "id": "f5d9dd723bd3826a",
                "name": "DynamoDB",
                "start_time": 1496958123.115,
                "end_time": 1496958124.016,
                "http": {
                  "response": {
                    "status": 200
                  }
                },
                "aws": {
                  "operation": "PutItem",
                  "region": "us-east-1",
                  "request_id": "7HVH8CKMJ6VAKB8NF89BMJV4R3VV4KQNSO5AEMVJF66Q9ASUAAJG",
                  "retries": 0,
                  "table_name": "PredictionsTable",
                  "resource_names": [
                    "PredictionsTable"
                  ]
                },
                "namespace": "aws",
                "subsegments": [
                  {
                    "id": "e5a7cb1448902158",
                    "name": "DynamoDBCostradamus",
                    "start_time": 1496958124.017,
                    "end_time": 1496958124.017,
                    "metadata": {
                      "DynamoDBCostradamus": {
                        "consumptions": {
                          "CapacityUnits": {
                            "val": 1,
                            "type": "WCU"
                          },
                          "PayloadSize": {
                            "val": 182,
                            "type": "B"
                          },
                          "Latency": {
                            "val": 902,
                            "type": "MS"
                          }
                        }
                      }
                    },
                    "cost": {
                      "MonetaryCost": {
                        "type": "NANO-USD",
                        "val": 181
                      },
                      "ProvisioningAmountWaste": {
                        "type": "B",
                        "val": 9818
                      },
                      "ProvisioningTimeWaste": {
                        "type": "MS",
                        "val": 3599098
                      },
                      "MeteringAmountWaste": {
                        "type": "B",
                        "val": 818
                      },
                      "MeteringTimeWaste": {
                        "type": "MS",
                        "val": 98
                      }
                    }
                  }
                ],
                "consumptions": {
                  "CapacityUnits": {
                    "val": 1,
                    "type": "WCU"
                  },
                  "PayloadSize": {
                    "val": 182,
                    "type": "B"
                  },
                  "Latency": {
                    "val": 902,
                    "type": "MS"
                  }
                },
                "cost": {
                  "MonetaryCost": {
                    "type": "NANO-USD",
                    "val": 181
                  },
                  "ProvisioningAmountWaste": {
                    "type": "B",
                    "val": 9818
                  },
                  "ProvisioningTimeWaste": {
                    "type": "MS",
                    "val": 3599098
                  },
                  "MeteringAmountWaste": {
                    "type": "B",
                    "val": 818
                  },
                  "MeteringTimeWaste": {
                    "type": "MS",
                    "val": 98
                  }
                }
              },
              {
                "id": "a7bc977727e5ef8f",
                "name": "DynamoDB",
                "start_time": 1496958123.222,
                "end_time": 1496958124.015,
                "http": {
                  "response": {
                    "status": 200
                  }
                },
                "aws": {
                  "operation": "PutItem",
                  "region": "us-east-1",
                  "request_id": "2IR5CJUA4S6LJ4UDC48S9CUQ1VVV4KQNSO5AEMVJF66Q9ASUAAJG",
                  "retries": 0,
                  "table_name": "PredictionsTable",
                  "resource_names": [
                    "PredictionsTable"
                  ]
                },
                "namespace": "aws",
                "subsegments": [
                  {
                    "id": "86b39c8b44450d7b",
                    "name": "DynamoDBCostradamus",
                    "start_time": 1496958124.015,
                    "end_time": 1496958124.015,
                    "metadata": {
                      "DynamoDBCostradamus": {
                        "consumptions": {
                          "CapacityUnits": {
                            "val": 1,
                            "type": "WCU"
                          },
                          "PayloadSize": {
                            "val": 182,
                            "type": "B"
                          },
                          "Latency": {
                            "val": 794,
                            "type": "MS"
                          }
                        }
                      }
                    },
                    "cost": {
                      "MonetaryCost": {
                        "type": "NANO-USD",
                        "val": 181
                      },
                      "ProvisioningAmountWaste": {
                        "type": "B",
                        "val": 9818
                      },
                      "ProvisioningTimeWaste": {
                        "type": "MS",
                        "val": 3599206
                      },
                      "MeteringAmountWaste": {
                        "type": "B",
                        "val": 818
                      },
                      "MeteringTimeWaste": {
                        "type": "MS",
                        "val": 206
                      }
                    }
                  }
                ],
                "consumptions": {
                  "CapacityUnits": {
                    "val": 1,
                    "type": "WCU"
                  },
                  "PayloadSize": {
                    "val": 182,
                    "type": "B"
                  },
                  "Latency": {
                    "val": 794,
                    "type": "MS"
                  }
                },
                "cost": {
                  "MonetaryCost": {
                    "type": "NANO-USD",
                    "val": 181
                  },
                  "ProvisioningAmountWaste": {
                    "type": "B",
                    "val": 9818
                  },
                  "ProvisioningTimeWaste": {
                    "type": "MS",
                    "val": 3599206
                  },
                  "MeteringAmountWaste": {
                    "type": "B",
                    "val": 818
                  },
                  "MeteringTimeWaste": {
                    "type": "MS",
                    "val": 206
                  }
                }
              },
              {
                "id": "ec7821a22af6a5e0",
                "name": "DynamoDB",
                "start_time": 1496958123.225,
                "end_time": 1496958123.935,
                "http": {
                  "response": {
                    "status": 200
                  }
                },
                "aws": {
                  "operation": "PutItem",
                  "region": "us-east-1",
                  "request_id": "K1FS7AM9BJVOB2PDOAK3PME9IRVV4KQNSO5AEMVJF66Q9ASUAAJG",
                  "retries": 0,
                  "table_name": "PredictionsTable",
                  "resource_names": [
                    "PredictionsTable"
                  ]
                },
                "namespace": "aws",
                "subsegments": [
                  {
                    "id": "e42c6833baaa24af",
                    "name": "DynamoDBCostradamus",
                    "start_time": 1496958123.935,
                    "end_time": 1496958123.935,
                    "metadata": {
                      "DynamoDBCostradamus": {
                        "consumptions": {
                          "CapacityUnits": {
                            "val": 1,
                            "type": "WCU"
                          },
                          "PayloadSize": {
                            "val": 182,
                            "type": "B"
                          },
                          "Latency": {
                            "val": 711,
                            "type": "MS"
                          }
                        }
                      }
                    },
                    "cost": {
                      "MonetaryCost": {
                        "type": "NANO-USD",
                        "val": 181
                      },
                      "ProvisioningAmountWaste": {
                        "type": "B",
                        "val": 9818
                      },
                      "ProvisioningTimeWaste": {
                        "type": "MS",
                        "val": 3599289
                      },
                      "MeteringAmountWaste": {
                        "type": "B",
                        "val": 818
                      },
                      "MeteringTimeWaste": {
                        "type": "MS",
                        "val": 289
                      }
                    }
                  }
                ],
                "consumptions": {
                  "CapacityUnits": {
                    "val": 1,
                    "type": "WCU"
                  },
                  "PayloadSize": {
                    "val": 182,
                    "type": "B"
                  },
                  "Latency": {
                    "val": 711,
                    "type": "MS"
                  }
                },
                "cost": {
                  "MonetaryCost": {
                    "type": "NANO-USD",
                    "val": 181
                  },
                  "ProvisioningAmountWaste": {
                    "type": "B",
                    "val": 9818
                  },
                  "ProvisioningTimeWaste": {
                    "type": "MS",
                    "val": 3599289
                  },
                  "MeteringAmountWaste": {
                    "type": "B",
                    "val": 818
                  },
                  "MeteringTimeWaste": {
                    "type": "MS",
                    "val": 289
                  }
                }
              },
              {
                "id": "0645254f0a33057a",
                "name": "DynamoDBCostradamus",
                "start_time": 1496958122.769,
                "end_time": 1496958122.769,
                "metadata": {
                  "DynamoDBCostradamus": {
                    "consumptions": {
                      "CapacityUnits": {
                        "val": 0.5,
                        "type": "RCU"
                      },
                      "PayloadSize": {
                        "val": 907,
                        "type": "B"
                      },
                      "Latency": {
                        "val": 2274,
                        "type": "MS"
                      }
                    }
                  }
                },
                "cost": {
                  "MonetaryCost": {
                    "type": "NANO-USD",
                    "val": 54
                  },
                  "ProvisioningAmountWaste": {
                    "type": "B",
                    "val": 199093
                  },
                  "ProvisioningTimeWaste": {
                    "type": "MS",
                    "val": 3597726
                  },
                  "MeteringAmountWaste": {
                    "type": "B",
                    "val": 3093
                  },
                  "MeteringTimeWaste": {
                    "type": "MS",
                    "val": 726
                  }
                }
              },
              {
                "id": "1c6ea45ed3ce211e",
                "name": "Kinesis",
                "start_time": 1496958123.017,
                "end_time": 1496958124.077,
                "http": {
                  "response": {
                    "status": 200
                  }
                },
                "aws": {
                  "operation": "PutRecord",
                  "region": "us-east-1",
                  "request_id": "d29089fe-53fc-8dc7-8323-4f15fce6aba1",
                  "retries": 0
                },
                "namespace": "aws",
                "subsegments": [
                  {
                    "id": "a31fa7666f79aebc",
                    "name": "KinesisCostradamus",
                    "start_time": 1496958124.078,
                    "end_time": 1496958124.078,
                    "metadata": {
                      "KinesisCostradamus": {
                        "consumptions": {
                          "PayloadSize": {
                            "val": 182,
                            "type": "B"
                          },
                          "Operation": {
                            "val": "WRITE",
                            "type": "KINESISOPERATION"
                          },
                          "Latency": {
                            "val": 1060,
                            "type": "MS"
                          }
                        }
                      }
                    },
                    "cost": {
                      "MonetaryCost": {
                        "type": "NANO-USD",
                        "val": 236
                      }
                    }
                  }
                ],
                "consumptions": {
                  "PayloadSize": {
                    "val": 182,
                    "type": "B"
                  },
                  "Operation": {
                    "val": "WRITE",
                    "type": "KINESISOPERATION"
                  },
                  "Latency": {
                    "val": 1060,
                    "type": "MS"
                  }
                },
                "cost": {
                  "MonetaryCost": {
                    "type": "NANO-USD",
                    "val": 236
                  }
                }
              },
              {
                "id": "e2671a22317c2d68",
                "name": "Kinesis",
                "start_time": 1496958123.223,
                "end_time": 1496958124.013,
                "http": {
                  "response": {
                    "status": 200
                  }
                },
                "aws": {
                  "operation": "PutRecord",
                  "region": "us-east-1",
                  "request_id": "d5956716-7c43-780e-8426-a1fd7ace684f",
                  "retries": 0
                },
                "namespace": "aws",
                "subsegments": [
                  {
                    "id": "5dc39f8f51dfcd0b",
                    "name": "KinesisCostradamus",
                    "start_time": 1496958124.014,
                    "end_time": 1496958124.014,
                    "metadata": {
                      "KinesisCostradamus": {
                        "consumptions": {
                          "PayloadSize": {
                            "val": 182,
                            "type": "B"
                          },
                          "Operation": {
                            "val": "WRITE",
                            "type": "KINESISOPERATION"
                          },
                          "Latency": {
                            "val": 790,
                            "type": "MS"
                          }
                        }
                      }
                    },
                    "cost": {
                      "MonetaryCost": {
                        "type": "NANO-USD",
                        "val": 118
                      }
                    }
                  }
                ],
                "consumptions": {
                  "PayloadSize": {
                    "val": 182,
                    "type": "B"
                  },
                  "Operation": {
                    "val": "WRITE",
                    "type": "KINESISOPERATION"
                  },
                  "Latency": {
                    "val": 790,
                    "type": "MS"
                  }
                },
                "cost": {
                  "MonetaryCost": {
                    "type": "NANO-USD",
                    "val": 118
                  }
                }
              },
              {
                "id": "f34ef4a28887af5c",
                "name": "Kinesis",
                "start_time": 1496958123.356,
                "end_time": 1496958123.874,
                "http": {
                  "response": {
                    "status": 200
                  }
                },
                "aws": {
                  "operation": "PutRecord",
                  "region": "us-east-1",
                  "request_id": "c7e47080-4dc1-7bfc-9657-b66b83d251f8",
                  "retries": 0
                },
                "namespace": "aws",
                "subsegments": [
                  {
                    "id": "a61a8a1e9ebd6927",
                    "name": "KinesisCostradamus",
                    "start_time": 1496958123.874,
                    "end_time": 1496958123.874,
                    "metadata": {
                      "KinesisCostradamus": {
                        "consumptions": {
                          "PayloadSize": {
                            "val": 182,
                            "type": "B"
                          },
                          "Operation": {
                            "val": "WRITE",
                            "type": "KINESISOPERATION"
                          },
                          "Latency": {
                            "val": 519,
                            "type": "MS"
                          }
                        }
                      }
                    },
                    "cost": {
                      "MonetaryCost": {
                        "type": "NANO-USD",
                        "val": 118
                      }
                    }
                  }
                ],
                "consumptions": {
                  "PayloadSize": {
                    "val": 182,
                    "type": "B"
                  },
                  "Operation": {
                    "val": "WRITE",
                    "type": "KINESISOPERATION"
                  },
                  "Latency": {
                    "val": 519,
                    "type": "MS"
                  }
                },
                "cost": {
                  "MonetaryCost": {
                    "type": "NANO-USD",
                    "val": 118
                  }
                }
              }
            ],
            "consumptions": {
              "CapacityUnits": {
                "val": 0.5,
                "type": "RCU"
              },
              "PayloadSize": {
                "val": 907,
                "type": "B"
              },
              "Latency": {
                "val": 2274,
                "type": "MS"
              }
            },
            "cost": {
              "MonetaryCost": {
                "type": "NANO-USD",
                "val": 54
              },
              "ProvisioningAmountWaste": {
                "type": "B",
                "val": 199093
              },
              "ProvisioningTimeWaste": {
                "type": "MS",
                "val": 3597726
              },
              "MeteringAmountWaste": {
                "type": "B",
                "val": 3093
              },
              "MeteringTimeWaste": {
                "type": "MS",
                "val": 726
              }
            }
          }
        ],
        "consumptions": {
          "Duration": {
            "val": 3905,
            "type": "ms"
          },
          "BilledDuration": {
            "val": 4000,
            "type": "ms"
          },
          "MemorySize": {
            "val": 128,
            "type": "MB"
          },
          "MaxMemoryUsed": {
            "val": 43,
            "type": "MB"
          }
        },
        "cost": {
          "MonetaryCost": {
            "type": "NANO-USD",
            "val": 8320
          },
          "ProvisioningAmountWaste": {
            "type": "B",
            "val": 0
          },
          "ProvisioningTimeWaste": {
            "type": "MS",
            "val": 0
          },
          "MeteringAmountWaste": {
            "type": "MB",
            "val": 85
          },
          "MeteringTimeWaste": {
            "type": "MS",
            "val": 95
          }
        }
      }
    },
    {
      "Id": "35cf55ca9bfe555e",
      "Document": {
        "id": "35cf55ca9bfe555e",
        "name": "ingestValueFunction",
        "start_time": 1496958115.817,
        "end_time": 1496958116.062,
        "http": {
          "response": {
            "status": 200
          }
        },
        "aws": {
          "request_id": "4adf4869-4c93-11e7-a18a-532955ff83a2"
        },
        "trace_id": "1-5939c4a3-08104439b1999caa32468f78",
        "origin": "AWS::Lambda",
        "resource_arn": "arn:aws:lambda:us-east-1:797753712737:function:ingestValueFunction"
      }
    },
    {
      "Id": "6370e80da7a12c33",
      "Document": {
        "id": "6370e80da7a12c33",
        "name": "persistValueFunction",
        "start_time": 1496958115.991,
        "end_time": 1496958116.003,
        "parent_id": "a82aabbfcde2e782",
        "http": {
          "response": {
            "status": 202
          }
        },
        "aws": {
          "request_id": "4af9d5cc-4c93-11e7-8914-ebf44942154e"
        },
        "trace_id": "1-5939c4a3-08104439b1999caa32468f78",
        "origin": "AWS::Lambda",
        "resource_arn": "arn:aws:lambda:us-east-1:797753712737:function:persistValueFunction",
        "subsegments": [
          {
            "id": "6915bd5adf047756",
            "name": "Attempt #1",
            "start_time": 1496958116.029,
            "end_time": 1496958116.108,
            "http": {
              "response": {
                "status": 200
              }
            }
          },
          {
            "id": "6096f0680ef0a0cb",
            "name": "Dwell Time",
            "start_time": 1496958115.991,
            "end_time": 1496958116.029,
            "http": {
              "response": {}
            }
          }
        ]
      }
    },
    {
      "Id": "32e766bd126e6f71",
      "Document": {
        "id": "32e766bd126e6f71",
        "name": "DynamoDB",
        "start_time": 1496958116.042,
        "end_time": 1496958116.107,
        "parent_id": "877ef218a4249b61",
        "inferred": true,
        "http": {
          "response": {
            "status": 200
          }
        },
        "aws": {
          "operation": "PutItem",
          "region": "us-east-1",
          "request_id": "9UVLM259BBJSO3FMTON9OE8T4BVV4KQNSO5AEMVJF66Q9ASUAAJG",
          "retries": 0,
          "table_name": "ValuesTable",
          "resource_names": [
            "ValuesTable"
          ]
        },
        "trace_id": "1-5939c4a3-08104439b1999caa32468f78",
        "origin": "AWS::DynamoDB::Table"
      }
    },
    {
      "Id": "07882df0169323cb",
      "Document": {
        "id": "07882df0169323cb",
        "name": "DynamoDB",
        "start_time": 1496958120.494,
        "end_time": 1496958122.768,
        "parent_id": "5661694f9e3a2899",
        "inferred": true,
        "http": {
          "response": {
            "status": 200
          }
        },
        "aws": {
          "operation": "Query",
          "region": "us-east-1",
          "request_id": "U2QUEA877F5LBJQJ1ATCIE3N1JVV4KQNSO5AEMVJF66Q9ASUAAJG",
          "retries": 0,
          "limit": 100,
          "select": "ALL_ATTRIBUTES",
          "table_name": "ValuesTable",
          "resource_names": [
            "ValuesTable"
          ]
        },
        "trace_id": "1-5939c4a3-08104439b1999caa32468f78",
        "origin": "AWS::DynamoDB::Table"
      }
    },
    {
      "Id": "21d0d7ff071afe23",
      "Document": {
        "id": "21d0d7ff071afe23",
        "name": "DynamoDB",
        "start_time": 1496958122.919,
        "end_time": 1496958123.875,
        "parent_id": "9fc72bf133c0bdec",
        "inferred": true,
        "http": {
          "response": {
            "status": 200
          }
        },
        "aws": {
          "operation": "PutItem",
          "region": "us-east-1",
          "request_id": "7C1QGS6QQ9AGDVN6E4V8L6KP0JVV4KQNSO5AEMVJF66Q9ASUAAJG",
          "retries": 0,
          "table_name": "PredictionsTable",
          "resource_names": [
            "PredictionsTable"
          ]
        },
        "trace_id": "1-5939c4a3-08104439b1999caa32468f78",
        "origin": "AWS::DynamoDB::Table"
      }
    },
    {
      "Id": "136b2e940a35fb8c",
      "Document": {
        "id": "136b2e940a35fb8c",
        "name": "Kinesis",
        "start_time": 1496958123.175,
        "end_time": 1496958123.834,
        "parent_id": "dd5cb3f46b38aa20",
        "inferred": true,
        "http": {
          "response": {
            "status": 200
          }
        },
        "aws": {
          "operation": "PutRecord",
          "region": "us-east-1",
          "request_id": "eb0973f8-bc00-e9ca-baba-b5137213c3ce",
          "retries": 0
        },
        "trace_id": "1-5939c4a3-08104439b1999caa32468f78",
        "origin": "AWS::Kinesis"
      }
    },
    {
      "Id": "0701bb0b3126cbe8",
      "Document": {
        "id": "0701bb0b3126cbe8",
        "name": "DynamoDB",
        "start_time": 1496958123.115,
        "end_time": 1496958124.016,
        "parent_id": "f5d9dd723bd3826a",
        "inferred": true,
        "http": {
          "response": {
            "status": 200
          }
        },
        "aws": {
          "operation": "PutItem",
          "region": "us-east-1",
          "request_id": "7HVH8CKMJ6VAKB8NF89BMJV4R3VV4KQNSO5AEMVJF66Q9ASUAAJG",
          "retries": 0,
          "table_name": "PredictionsTable",
          "resource_names": [
            "PredictionsTable"
          ]
        },
        "trace_id": "1-5939c4a3-08104439b1999caa32468f78",
        "origin": "AWS::DynamoDB::Table"
      }
    },
    {
      "Id": "366666ab1ca8ff35",
      "Document": {
        "id": "366666ab1ca8ff35",
        "name": "DynamoDB",
        "start_time": 1496958123.222,
        "end_time": 1496958124.015,
        "parent_id": "a7bc977727e5ef8f",
        "inferred": true,
        "http": {
          "response": {
            "status": 200
          }
        },
        "aws": {
          "operation": "PutItem",
          "region": "us-east-1",
          "request_id": "2IR5CJUA4S6LJ4UDC48S9CUQ1VVV4KQNSO5AEMVJF66Q9ASUAAJG",
          "retries": 0,
          "table_name": "PredictionsTable",
          "resource_names": [
            "PredictionsTable"
          ]
        },
        "trace_id": "1-5939c4a3-08104439b1999caa32468f78",
        "origin": "AWS::DynamoDB::Table"
      }
    },
    {
      "Id": "3629e8d73a2cf5ad",
      "Document": {
        "id": "3629e8d73a2cf5ad",
        "name": "DynamoDB",
        "start_time": 1496958123.225,
        "end_time": 1496958123.935,
        "parent_id": "ec7821a22af6a5e0",
        "inferred": true,
        "http": {
          "response": {
            "status": 200
          }
        },
        "aws": {
          "operation": "PutItem",
          "region": "us-east-1",
          "request_id": "K1FS7AM9BJVOB2PDOAK3PME9IRVV4KQNSO5AEMVJF66Q9ASUAAJG",
          "retries": 0,
          "table_name": "PredictionsTable",
          "resource_names": [
            "PredictionsTable"
          ]
        },
        "trace_id": "1-5939c4a3-08104439b1999caa32468f78",
        "origin": "AWS::DynamoDB::Table"
      }
    },
    {
      "Id": "0d6e27623ca4569a",
      "Document": {
        "id": "0d6e27623ca4569a",
        "name": "Kinesis",
        "start_time": 1496958123.017,
        "end_time": 1496958124.077,
        "parent_id": "1c6ea45ed3ce211e",
        "inferred": true,
        "http": {
          "response": {
            "status": 200
          }
        },
        "aws": {
          "operation": "PutRecord",
          "region": "us-east-1",
          "request_id": "d29089fe-53fc-8dc7-8323-4f15fce6aba1",
          "retries": 0
        },
        "trace_id": "1-5939c4a3-08104439b1999caa32468f78",
        "origin": "AWS::Kinesis"
      }
    },
    {
      "Id": "26ea986d3e941c3d",
      "Document": {
        "id": "26ea986d3e941c3d",
        "name": "Kinesis",
        "start_time": 1496958123.223,
        "end_time": 1496958124.013,
        "parent_id": "e2671a22317c2d68",
        "inferred": true,
        "http": {
          "response": {
            "status": 200
          }
        },
        "aws": {
          "operation": "PutRecord",
          "region": "us-east-1",
          "request_id": "d5956716-7c43-780e-8426-a1fd7ace684f",
          "retries": 0
        },
        "trace_id": "1-5939c4a3-08104439b1999caa32468f78",
        "origin": "AWS::Kinesis"
      }
    },
    {
      "Id": "3441156807b59a49",
      "Document": {
        "id": "3441156807b59a49",
        "name": "Kinesis",
        "start_time": 1496958123.356,
        "end_time": 1496958123.874,
        "parent_id": "f34ef4a28887af5c",
        "inferred": true,
        "http": {
          "response": {
            "status": 200
          }
        },
        "aws": {
          "operation": "PutRecord",
          "region": "us-east-1",
          "request_id": "c7e47080-4dc1-7bfc-9657-b66b83d251f8",
          "retries": 0
        },
        "trace_id": "1-5939c4a3-08104439b1999caa32468f78",
        "origin": "AWS::Kinesis"
      }
    }
  ]
}